nbdev_template/__init__.py
nbdev_template/_nbdev.py
nbdev_template/core.py
nbdev_template-0.0.10.dist-info/LICENSE
nbdev_template-0.0.10.dist-info/METADATA
nbdev_template-0.0.10.dist-info/WHEEL
nbdev_template-0.0.10.dist-info/entry_points.txt
nbdev_template-0.0.10.dist-info/top_level.txt
nbdev_template-0.0.10.dist-info/RECORD
