Metadata-Version: 2.1
Name: nbdev-template
Version: 0.0.10
Summary: <ADD DESCRIPTION>
Home-page: https://github.com/ELC/nbdev_template/tree/master/
Author: Ezequiel Castaño
Author-email: castanoezequielleonardo@gmail.com
License: Apache Software License 2.0
Keywords: <ADD KEYWORDS>
Platform: UNKNOWN
Classifier: Development Status :: 2 - Pre-Alpha
Classifier: Intended Audience :: Developers
Classifier: License :: OSI Approved :: Apache Software License
Classifier: Natural Language :: English
Classifier: Programming Language :: Python :: 3.6
Classifier: Programming Language :: Python :: 3.7
Classifier: Programming Language :: Python :: 3.8
Classifier: Programming Language :: Python :: 3.9
Requires-Python: >=3.6
